awesome_calculator/__init__.py
awesome_calculator/main.py
awesome_calculator-1.2.3.dist-info/licenses/LICENSE
awesome_calculator-1.2.3.dist-info/METADATA
awesome_calculator-1.2.3.dist-info/WHEEL
awesome_calculator-1.2.3.dist-info/entry_points.txt
awesome_calculator-1.2.3.dist-info/top_level.txt
awesome_calculator-1.2.3.dist-info/RECORD
