Metadata-Version: 2.4
Name: awesome-calculator
Version: 1.2.3
Summary: A colorful CLI calculator with math operations and colorama
Home-page: https://github.com/abhigyan-709/awesome_calculator
Author: Project DevOps
Author-email: projectdevops709@gmail.com
License: MIT
Classifier: Programming Language :: Python :: 3
Classifier: License :: OSI Approved :: MIT License
Classifier: Operating System :: OS Independent
Requires-Python: >=3.6
License-File: LICENSE
Requires-Dist: colorama
Dynamic: license-file
